{"skeleton":{"hash":"FVkIoJuBr1I","spine":"4.2.40","x":-351.38,"y":434.95,"width":239,"height":98,"images":"../2-1_Tile_Purple/images/","audio":""},"bones":[{"name":"root"},{"name":"Tile_Purple","parent":"root","length":104.65,"x":-280.07,"y":484.37},{"name":"Tile_Purple_S","parent":"Tile_Purple","x":60.15,"y":-15.16}],"slots":[{"name":"Tile_Purple_S","bone":"Tile_Purple_S","attachment":"Tile_Purple_S","blend":"multiply"},{"name":"Tile_Purple","bone":"Tile_Purple","attachment":"Tile_Purple","blend":"screen"}],"skins":[{"name":"default","attachments":{"Tile_Purple":{"Tile_Purple":{"x":48.19,"y":1.58,"width":239,"height":94}},"Tile_Purple_S":{"Tile_Purple_S":{"x":-8.95,"y":5.24,"width":227,"height":79}}}}],"animations":{"Tile_Purple":{"slots":{"Tile_Purple":{"rgba":[{"color":"ffffff2d"},{"time":7.7,"color":"ffffffff"},{"time":18.3667,"color":"ffffff00"},{"time":20,"color":"ffffff2d"}]},"Tile_Purple_S":{"rgba":[{"color":"ffffff2d"},{"time":7.7,"color":"ffffffff"},{"time":18.3667,"color":"ffffff00"},{"time":20,"color":"ffffff2d"}]}}}}}