<?xml version="1.0" encoding="UTF-8"?>
<objects serializationModel="Studio.02.03.00">
	<object class="AudioFile" id="{d1ca86dc-007b-4d3e-a5ee-cafb4f7c57c6}">
		<property name="assetPath">
			<value>GuitarShield_Ani_Sound.mp3</value>
		</property>
		<property name="frequencyInKHz">
			<value>48</value>
		</property>
		<property name="channelCount">
			<value>2</value>
		</property>
		<property name="length">
			<value>0.93600000000000005</value>
		</property>
		<relationship name="masterAssetFolder">
			<destination>{0831842f-2f26-4b75-ac61-331ff0498d03}</destination>
		</relationship>
	</object>
</objects>
